dither_go-0.4.0.dist-info/RECORD
dither_go-0.4.0.dist-info/WHEEL
dither_go-0.4.0.dist-info/COPYING
dither_go-0.4.0.dist-info/top_level.txt
dither_go-0.4.0.dist-info/METADATA
dither_go/wrapper.py
dither_go/matrices.py
dither_go/__init__.py
dither_go/exceptions.py
dither_go/utils/color.py
dither_go/utils/matrices.py
dither_go/utils/__init__.py
dither_go/bindings/build.py
dither_go/bindings/_dither_go.cpython-311-darwin.so
dither_go/bindings/dither_go.py
dither_go/bindings/dither.py
dither_go/bindings/dither_go.go
dither_go/bindings/_dither_go.cpython-311-darwin.h
dither_go/bindings/__init__.py
dither_go/bindings/dither_go.c
dither_go/bindings/go.py
dither_go/bindings/dither_go_go.h
