Metadata-Version: 2.1
Name: dither-go
Version: 0.4.0
Summary: A fast and the most correct image dithering library
Author: tfuxu
Project-URL: Homepage, https://github.com/tfuxu/dither-go
Project-URL: Bug Tracker, https://github.com/tfuxu/dither-go/issues
Keywords: golang,bindings,dithering,processing
Classifier: Development Status :: 3 - Alpha
Classifier: Programming Language :: Python :: 3
Classifier: Programming Language :: Python :: 3 :: Only
Classifier: Programming Language :: Python :: 3.8
Classifier: Programming Language :: Python :: 3.9
Classifier: Programming Language :: Python :: 3.10
Classifier: Programming Language :: Python :: 3.11
Classifier: License :: OSI Approved :: GNU General Public License v3 or later (GPLv3+)
Classifier: Operating System :: OS Independent
Classifier: Topic :: Multimedia :: Graphics
Classifier: Topic :: Multimedia :: Graphics :: Graphics Conversion
Requires-Python: >=3.8
License-File: COPYING
Requires-Dist: simple-parsing
